{
	"type": "minecraft:command",
	"pools": [
		{
			"rolls": 1,
			"entries": [
				{
					"type": "minecraft:item",
					"name": "minecraft:carrot_on_a_stick",
					"functions": [
						{
							"function": "minecraft:set_name",
							"entity": "this",
							"name": {
								"translate": "ssbrc.tooltips.mega_man.air_shooter",
								"color": "blue",
								"bold": true,
								"italic": false
							}
						},
						{
							"function": "minecraft:reference",
							"name": "ssbrc:fighters/init/preset/ranged"
						},
						{
							"function": "minecraft:set_lore",
							"entity": "this",
							"lore": [
								{
									"text": "- [",
									"color": "gray",
									"bold": false,
									"italic": false,
									"extra": [
										{
											"keybind": "key.use",
											"color": "gray",
											"bold": false,
											"italic": false
										},
										{
											"translate": "ssbrc.tooltips.ability.activate",
											"color": "gray",
											"bold": false,
											"italic": false
										}
									]
								}
							],
							"replace": false
						},
						{
							"function": "minecraft:set_nbt",
							"tag": "{air_shooter:1}"
						}
					]
				}
			]
		}
	]
}
