{
	"type": "minecraft:command",
	"pools": [
		{
			"rolls": 1,
			"entries": [
				{
					"type": "minecraft:item",
					"name": "minecraft:shield",
					"functions": [
						{
							"function": "minecraft:copy_nbt",
							"source": {
								"type": "minecraft:storage",
								"source": "ssbrc:hylian_shield"
							},
							"ops": [
								{
									"source": "damage",
									"target": "Damage",
									"op": "replace"
								}
							]
						},
						{
							"function": "minecraft:reference",
							"name": "ssbrc:fighters/init/preset/defensive"
						},
						{
							"function": "minecraft:reference",
							"name": "ssbrc:fighters/toon_link/hylian_shield/default",
							"conditions": [
								{
									"condition": "minecraft:inverted",
									"term": {
										"condition": "minecraft:entity_properties",
										"entity": "this",
										"predicate": {
											"nbt": "{Tags:[\"gold\"]}"
										}
									}
								}
							]
						},
						{
							"function": "minecraft:reference",
							"name": "ssbrc:fighters/toon_link/hylian_shield/gold",
							"conditions": [
								{
									"condition": "minecraft:entity_properties",
									"entity": "this",
									"predicate": {
										"nbt": "{Tags:[\"gold\"]}"
									}
								}
							]
						},
						{
							"function": "minecraft:set_nbt",
							"tag": "{hylianShield:1}"
						}
					]
				}
			]
		}
	]
}
