{
	"type": "minecraft:command",
	"pools": [
		{
			"rolls": 1,
			"entries": [
				{
					"type": "minecraft:item",
					"name": "minecraft:nether_star",
					"functions": [
						{
							"function": "minecraft:set_name",
							"entity": "this",
							"name": {
								"translate": "ssbrc.tooltips.zelda.dungeonItem.magic_boomerang",
								"color": "blue",
								"bold": true,
								"italic": false
							}
						},
						{
							"function": "minecraft:reference",
							"name": "ssbrc:fighters/init/preset/magic"
						},
						{
							"function": "minecraft:reference",
							"name": "ssbrc:fighters/link/boomerang/tooltip"
						},
						{
							"function": "minecraft:set_lore",
							"entity": "this",
							"lore": [
								{
									"translate": "ssbrc.tooltips.zelda.dungeonItem.magic_boomerang.description.1",
									"color": "gray",
									"bold": false,
									"italic": false
								}
							],
							"mode": "append"
						},
						{
							"function": "minecraft:set_custom_model_data",
							"value": 9031
						},
						{
							"function": "minecraft:set_custom_data",
							"tag": "{magic_boomerang:1}"
						}
					]
				}
			]
		}
	]
}
