{
	"type": "minecraft:command",
	"pools": [
		{
			"rolls": 1,
			"entries": [
				{
					"type": "minecraft:item",
					"name": "minecraft:iron_axe",
					"functions": [
						{
							"function": "minecraft:set_name",
							"entity": "this",
							"name": {
								"translate": "ssbrc.tooltips.jigglypuff.pound",
								"color": "white",
								"bold": true,
								"italic": false
							}
						},
						{
							"function": "minecraft:set_components",
							"components": {
								"minecraft:attribute_modifiers": {
									"modifiers": [
										{
											"type": "minecraft:generic.attack_damage",
											"uuid": [
												100000000,
												100000000,
												100000000,
												000000001
											],
											"name": "Attack Damage",
											"amount": 6,
											"operation": "add_multiplied_base",
											"slot": "mainhand"
										},
										{
											"type": "minecraft:generic.attack_speed",
											"uuid": [
												100000000,
												100000000,
												100000000,
												100000000
											],
											"name": "Attack Speed",
											"amount": 0.75,
											"operation": "add_multiplied_base",
											"slot": "mainhand"
										}
									],
									"show_in_tooltip": false
								},
								"minecraft:custom_data": "{item:\"pound\"}"
							}
						},
						{
							"function": "minecraft:reference",
							"name": "ssbrc:fighters/init/preset/melee"
						}
					]
				}
			]
		}
	]
}
