{
	"type": "minecraft:command",
	"pools": [
		{
			"rolls": 1,
			"entries": [
				{
					"type": "minecraft:item",
					"name": "minecraft:cod",
					"functions": [
						{
							"function": "minecraft:set_name",
							"entity": "this",
							"name": {
								"text": "Puftup",
								"color": "green",
								"bold": true,
								"italic": false
							}
						},
						{
							"function": "minecraft:set_lore",
							"entity": "this",
							"lore": [
								{
									"text": "Donkey Kong",
									"color": "gray",
									"bold": false,
									"italic": false
								}
							],
							"replace": true
						}
					]
				},
				{
					"type": "minecraft:item",
					"name": "minecraft:cod",
					"functions": [
						{
							"function": "minecraft:set_name",
							"entity": "this",
							"name": {
								"text": "Puftup",
								"color": "green",
								"bold": true,
								"italic": false
							}
						},
						{
							"function": "minecraft:set_lore",
							"entity": "this",
							"lore": [
								{
									"text": "Donkey Kong",
									"color": "gray",
									"bold": false,
									"italic": false
								}
							],
							"replace": true
						}
					]
				},
				{
					"type": "minecraft:item",
					"name": "minecraft:cod",
					"functions": [
						{
							"function": "minecraft:set_name",
							"entity": "this",
							"name": {
								"text": "Puftup",
								"color": "green",
								"bold": true,
								"italic": false
							}
						},
						{
							"function": "minecraft:set_lore",
							"entity": "this",
							"lore": [
								{
									"text": "Donkey Kong",
									"color": "gray",
									"bold": false,
									"italic": false
								}
							],
							"replace": true
						}
					]
				}
			]
		}
	]
}
