{
	"display": {
		"icon": {
			"item": "minecraft:barrier",
			"nbt": "{CustomModelData:380}"
		},
		"title": {
			"text": "Fox",
			"color": "white",
			"bold": true,
			"italic": false,
			"extra": [
				{
					"text": " Mastery",
					"color": "white",
					"bold": true,
					"italic": false
				}
			]
		},
		"description": {
			"text": "Complete challenges to unlock a reward!",
			"color": "gray",
			"bold": false,
			"italic": false
		},
		"frame": "challenge",
		"show_toast": false,
		"announce_to_chat": false,
		"background": "minecraft:textures/gui/advancements/backgrounds/stone.png"
	},
	"parent": "ssbrc:series/star_fox/root",
	"criteria": {
		"novice": {
			"trigger": "minecraft:impossible"
		},
		"veteran": {
			"trigger": "minecraft:impossible"
		},
		"survivalist": {
			"trigger": "minecraft:impossible"
		},
		"slayer": {
			"trigger": "minecraft:impossible"
		},
		"master": {
			"trigger": "minecraft:impossible"
		},
		"combat_zone": {
			"trigger": "minecraft:impossible"
		},
		"saurian_warrior": {
			"trigger": "minecraft:impossible"
		},
		"tournament_finals": {
			"trigger": "minecraft:impossible"
		},
		"trust_your_instincts": {
			"trigger": "minecraft:impossible"
		},
		"were_star_fox": {
			"trigger": "minecraft:impossible"
		}
	},
	"requirements": [
		[
			"novice"
		],
		[
			"veteran"
		],
		[
			"survivalist"
		],
		[
			"slayer"
		],
		[
			"master"
		],
		[
			"combat_zone"
		],
		[
			"saurian_warrior"
		],
		[
			"tournament_finals"
		],
		[
			"trust_your_instincts"
		],
		[
			"were_star_fox"
		]
	],
	"rewards": {
		"function": "ssbrc:advancements/fox/mastery"
	}
}
